zmanim/__init__.py
zmanim/astronomical_calendar.py
zmanim/exceptions/artic_circle.py
zmanim/hebrew_calendar/__init__.py
zmanim/hebrew_calendar/jewish_calendar.py
zmanim/hebrew_calendar/jewish_date.py
zmanim/limudim/__init__.py
zmanim/limudim/anchor.py
zmanim/limudim/anchors/__init__.py
zmanim/limudim/anchors/day_of_month_anchor.py
zmanim/limudim/anchors/day_of_year_anchor.py
zmanim/limudim/calculators/__init__.py
zmanim/limudim/calculators/daf_hashavua_bavli.py
zmanim/limudim/calculators/daf_yomi_bavli.py
zmanim/limudim/calculators/daf_yomi_yerushalmi.py
zmanim/limudim/calculators/mishna_yomis.py
zmanim/limudim/calculators/parsha.py
zmanim/limudim/calculators/pirkei_avos.py
zmanim/limudim/calculators/tehillim_monthly.py
zmanim/limudim/cycle.py
zmanim/limudim/interval.py
zmanim/limudim/limud.py
zmanim/limudim/limud_calculator.py
zmanim/limudim/unit.py
zmanim/util/__init__.py
zmanim/util/astronomical_calculations.py
zmanim/util/geo_location.py
zmanim/util/math_helper.py
zmanim/util/noaa_calculator.py
zmanim/util/sun_times_calculator.py
zmanim/zmanim_calendar.py
typed_zmanim-0.1.0.dist-info/LICENSE
typed_zmanim-0.1.0.dist-info/METADATA
typed_zmanim-0.1.0.dist-info/WHEEL
typed_zmanim-0.1.0.dist-info/RECORD
