Metadata-Version: 2.1
Name: typed-zmanim
Version: 0.1.0
Summary: A Typed Zmanim library for Python. Forked from pinnymz/python-zmanim
Home-page: https://github.com/dickermoshe/typed-zmanim
License: LGPL-2.1-or-later
Keywords: zmanim
Author: Moshe Dicker
Author-email: dickermoshe@gmail.com
Requires-Python: >=3.7,<4
Classifier: License :: OSI Approved
Classifier: License :: OSI Approved :: GNU Lesser General Public License v2 or later (LGPLv2+)
Classifier: Operating System :: OS Independent
Classifier: Programming Language :: Python :: 3
Classifier: Programming Language :: Python :: 3.7
Classifier: Programming Language :: Python :: 3.8
Classifier: Programming Language :: Python :: 3.9
Classifier: Programming Language :: Python :: 3.10
Classifier: Programming Language :: Python :: 3.11
Requires-Dist: julian (>=0.14,<0.15)
Requires-Dist: memoization (>=0.4.0,<0.5.0)
Requires-Dist: python-dateutil (>=2.8.2,<3.0.0)
Requires-Dist: types-python-dateutil (>=2.8.19.13,<3.0.0.0)
Project-URL: Repository, https://github.com/dickermoshe/typed-zmanim
